instarec/__init__.py
instarec/cli.py
instarec/downloader.py
instarec/instagram.py
instarec/interactive.py
instarec/io.py
instarec/live.py
instarec/log.py
instarec/loss_check.py
instarec/merger.py
instarec/mpd.py
instarec/past.py
instarec/progress_bar.py
instarec/utils.py
instarec-1.3.0.dist-info/licenses/LICENSE
instarec-1.3.0.dist-info/METADATA
instarec-1.3.0.dist-info/WHEEL
instarec-1.3.0.dist-info/entry_points.txt
instarec-1.3.0.dist-info/top_level.txt
instarec-1.3.0.dist-info/RECORD
