Metadata-Version: 2.4
Name: instarec
Version: 1.3.0
Summary: A tool to download Instagram live streams.
Author-email: qwer-lives <primary@qwerlives.com>
License-Expression: GPL-3.0-or-later
Classifier: Programming Language :: Python :: 3
Classifier: Operating System :: OS Independent
Classifier: Topic :: Multimedia :: Video :: Capture
Requires-Python: >=3.8
License-File: LICENSE
Requires-Dist: aiohttp
Requires-Dist: aiofiles
Requires-Dist: lxml
Requires-Dist: tqdm
Requires-Dist: platformdirs
Dynamic: license-file
